nustattools/__init__.py
nustattools/_version.py
nustattools/_version.pyi
nustattools/py.typed
nustattools/plotting/__init__.py
nustattools/plotting/_corplot.py
nustattools/plotting/_hinton.py
nustattools/stats/__init__.py
nustattools/stats/_derate.py
nustattools/stats/_dist.py
nustattools/stats/_fmax.py
nustattools/stats/gx2/.git
nustattools/stats/gx2/.gitignore
nustattools/stats/gx2/.gitmodules
nustattools/stats/gx2/LICENSE
nustattools/stats/gx2/README.md
nustattools/stats/gx2/functions.py
nustattools/stats/gx2/getting_started.ipynb
nustattools/stats/gx2/test_all.sh
nustattools/stats/gx2/test_all.txt
nustattools/stats/gx2/test_gx2inv.py
nustattools/stats/gx2/test_gx2stat.py
nustattools/stats/gx2/gx2-matlab/.gitignore
nustattools/stats/gx2/gx2-matlab/LICENSE
nustattools/stats/gx2/gx2-matlab/README.md
nustattools/stats/gx2/gx2-matlab/demos.xml
nustattools/stats/gx2/gx2-matlab/gx2_icon.png
nustattools/stats/gx2/gx2-matlab/gx2_params_norm_quad.m
nustattools/stats/gx2/gx2-matlab/gx2cdf.m
nustattools/stats/gx2/gx2-matlab/gx2cdf_davies.m
nustattools/stats/gx2/gx2-matlab/gx2cdf_imhof.m
nustattools/stats/gx2/gx2-matlab/gx2cdf_ruben.m
nustattools/stats/gx2/gx2-matlab/gx2inv.m
nustattools/stats/gx2/gx2-matlab/gx2pdf.m
nustattools/stats/gx2/gx2-matlab/gx2rnd.m
nustattools/stats/gx2/gx2-matlab/gx2stat.m
nustattools/stats/gx2/gx2-matlab/doc/GettingStarted.mlx
nustattools-0.8.0.dist-info/METADATA
nustattools-0.8.0.dist-info/WHEEL
nustattools-0.8.0.dist-info/licenses/LICENSE
nustattools-0.8.0.dist-info/RECORD
