Metadata-Version: 2.4
Name: nustattools
Version: 0.8.0
Summary: Statistical tools for neutrino physics
Project-URL: Homepage, https://github.com/ast0815/nustattools
Project-URL: Bug Tracker, https://github.com/ast0815/nustattools/issues
Project-URL: Discussions, https://github.com/ast0815/nustattools/discussions
Project-URL: Changelog, https://github.com/ast0815/nustattools/releases
Author-email: Lukas Koch <lukas.koch@mailbox.org>
License: Copyright 2024 Lukas Koch
License-File: LICENSE
Classifier: Development Status :: 1 - Planning
Classifier: Intended Audience :: Developers
Classifier: Intended Audience :: Science/Research
Classifier: License :: OSI Approved :: MIT License
Classifier: Operating System :: OS Independent
Classifier: Programming Language :: Python
Classifier: Programming Language :: Python :: 3
Classifier: Programming Language :: Python :: 3 :: Only
Classifier: Programming Language :: Python :: 3.8
Classifier: Programming Language :: Python :: 3.9
Classifier: Programming Language :: Python :: 3.10
Classifier: Programming Language :: Python :: 3.11
Classifier: Programming Language :: Python :: 3.12
Classifier: Programming Language :: Python :: 3.13
Classifier: Topic :: Scientific/Engineering
Classifier: Typing :: Typed
Requires-Python: >=3.8
Requires-Dist: numba>=0.58.1
Requires-Dist: numpy>=1.22.3
Requires-Dist: scipy>=1.8.0
Provides-Extra: dev
Requires-Dist: pytest-cov>=3; extra == 'dev'
Requires-Dist: pytest>=6; extra == 'dev'
Provides-Extra: docs
Requires-Dist: furo>=2023.08.17; extra == 'docs'
Requires-Dist: intersphinx-registry; extra == 'docs'
Requires-Dist: matplotlib>=3; extra == 'docs'
Requires-Dist: myst-parser>=0.13; extra == 'docs'
Requires-Dist: sphinx-autodoc-typehints; extra == 'docs'
Requires-Dist: sphinx-copybutton; extra == 'docs'
Requires-Dist: sphinx>=7.0; extra == 'docs'
Provides-Extra: plotting
Requires-Dist: matplotlib>=3; extra == 'plotting'
Provides-Extra: test
Requires-Dist: matplotlib>=3; extra == 'test'
Requires-Dist: pytest-cov>=3; extra == 'test'
Requires-Dist: pytest>=6; extra == 'test'
